activitylog/__init__.py
activitylog/admin.py
activitylog/admin_helpers.py
activitylog/apps.py
activitylog/backends.py
activitylog/crudhistory_admin_mixin.py
activitylog/models.py
activitylog/settings.py
activitylog/tests.py
activitylog/utils.py
django_activitylog_jwt-1.0.2.dist-info/METADATA
django_activitylog_jwt-1.0.2.dist-info/WHEEL
django_activitylog_jwt-1.0.2.dist-info/top_level.txt
django_activitylog_jwt-1.0.2.dist-info/RECORD
